llama/__init__.py
llama/generation.py
llama/model.py
llama/test_tokenizer.py
llama/tokenizer.py
meta_llama3-0.0.1.dist-info/LICENSE
meta_llama3-0.0.1.dist-info/METADATA
meta_llama3-0.0.1.dist-info/WHEEL
meta_llama3-0.0.1.dist-info/top_level.txt
meta_llama3-0.0.1.dist-info/RECORD
