Metadata-Version: 2.1
Name: meta-llama3
Version: 0.0.1
Summary: UNKNOWN
License: UNKNOWN
Platform: UNKNOWN
License-File: LICENSE
Requires-Dist: torch
Requires-Dist: fairscale
Requires-Dist: fire
Requires-Dist: tiktoken (==0.4.0)
Requires-Dist: blobfile
